{
  "publicPath": "/_nuxt/",
  "all": [
    "../server/index.spa.html",
    "../server/index.ssr.html",
    "01d7f9d27eba7963df98.js",
    "06808358708e16107f18.js",
    "06f03e3ab48b2fe3c4ae.js",
    "07d5f8d6bd27d8986f3b.js",
    "08f34f8696c8f9dbeadb.js",
    "0a13e0e6604faff23163.js",
    "11d2e6b9ac34f8d62a81.js",
    "161aa66f3cc68b4e2e52.js",
    "1b3a8e6f556870fc5881.js",
    "1dac18841524e3958b39.js",
    "20112602d2f6691dd0d4.js",
    "26a830646733ead97e3d.js",
    "2c0f8532e87016ce41d2.js",
    "2f3c4df1ae08bc03e36a.js",
    "36ad12cd4d7174123316.js",
    "36f5c75301bd2564e5cf.js",
    "512723d3b11b19cfa16e.js",
    "51417af977e5b8ef8dbc.js",
    "53e70fcc006def71c01c.js",
    "54a7108a1652b686d5c2.js",
    "5633b8480f31fbd5a51e.js",
    "5a2365d28863482a6c7b.js",
    "5eaf4242196a7f2f03b6.js",
    "636be5046d8705b5a92d.js",
    "6a51f1bae46034d6c0bc.js",
    "6b4ee8adb9e01183dfcd.js",
    "721f58e0b7e9d886ff3d.js",
    "72f205a2c97ec972885d.js",
    "75c18969087c74f071a5.js",
    "77a663722b3ce1f93f3b.js",
    "7a1418d0beef6763fb18.js",
    "8282956f8842e47fec94.js",
    "830745f8a4b5dbbf4023.js",
    "842979e2fed04f812316.js",
    "851e9a21e1d0294bcc09.js",
    "867f245d4b107bb48f7f.js",
    "868bf46e1434b8beaba6.js",
    "954094794ad91a69e9c1.js",
    "955d21512d42eecf2099.js",
    "LICENSES",
    "a240b5709022369269bf.js",
    "a2ee37bcfd77136dd8c7.js",
    "a8ff101f5ce3b1b48ab3.js",
    "ad785722db1783792c64.js",
    "b2cc4e1ee4c2836b836a.js",
    "b4c360ce821613a63e1b.js",
    "b746d4cc2dc0ab00733e.js",
    "bb6cd6d6a15a1a806e1a.js",
    "bbd4cd22d833e0692cd9.js",
    "c0b4c1673ad9346c55ed.js",
    "c30da9b7027f2249d20c.js",
    "c86dc8b58cc67c4e20b4.js",
    "cff5cc432f0e55792e33.js",
    "d1dfbbf09158a9998b4f.js",
    "d644d3c1963281a6d652.js",
    "d96dfe1dd1799e1795e9.js",
    "da81bc70878f076cecde.js",
    "dec8311b2870f1340085.js",
    "e0c75d23f0c37cda204a.js",
    "eb287ecebbcf1da088da.js",
    "eb30904e1fee603d2350.js",
    "f21aaad7776207136774.js",
    "f2f5e390dc17bf77c921.js",
    "f344b8f59173747c334b.js",
    "f4d3e419cab28b72017d.js",
    "fa29f9967d3fec15c8f5.js",
    "fb1f8025b0d5a05e0ad6.js",
    "fe8eb36dc9075a263c6b.js",
    "fonts/1865888.woff",
    "fonts/3ea4491.woff2",
    "fonts/7af8248.woff2",
    "fonts/868301b.woff",
    "fonts/a32e728.woff2",
    "fonts/a5bdf33.woff",
    "fonts/ae56123.woff",
    "fonts/d14aae9.woff2",
    "fonts/fb3ebff.woff"
  ],
  "initial": [
    "54a7108a1652b686d5c2.js",
    "dec8311b2870f1340085.js",
    "955d21512d42eecf2099.js",
    "bb6cd6d6a15a1a806e1a.js"
  ],
  "async": [
    "01d7f9d27eba7963df98.js",
    "06808358708e16107f18.js",
    "06f03e3ab48b2fe3c4ae.js",
    "07d5f8d6bd27d8986f3b.js",
    "08f34f8696c8f9dbeadb.js",
    "0a13e0e6604faff23163.js",
    "11d2e6b9ac34f8d62a81.js",
    "161aa66f3cc68b4e2e52.js",
    "1b3a8e6f556870fc5881.js",
    "1dac18841524e3958b39.js",
    "20112602d2f6691dd0d4.js",
    "26a830646733ead97e3d.js",
    "2c0f8532e87016ce41d2.js",
    "2f3c4df1ae08bc03e36a.js",
    "36ad12cd4d7174123316.js",
    "36f5c75301bd2564e5cf.js",
    "512723d3b11b19cfa16e.js",
    "51417af977e5b8ef8dbc.js",
    "53e70fcc006def71c01c.js",
    "5633b8480f31fbd5a51e.js",
    "5a2365d28863482a6c7b.js",
    "5eaf4242196a7f2f03b6.js",
    "636be5046d8705b5a92d.js",
    "6a51f1bae46034d6c0bc.js",
    "6b4ee8adb9e01183dfcd.js",
    "721f58e0b7e9d886ff3d.js",
    "72f205a2c97ec972885d.js",
    "75c18969087c74f071a5.js",
    "77a663722b3ce1f93f3b.js",
    "7a1418d0beef6763fb18.js",
    "8282956f8842e47fec94.js",
    "830745f8a4b5dbbf4023.js",
    "842979e2fed04f812316.js",
    "851e9a21e1d0294bcc09.js",
    "867f245d4b107bb48f7f.js",
    "868bf46e1434b8beaba6.js",
    "954094794ad91a69e9c1.js",
    "a240b5709022369269bf.js",
    "a2ee37bcfd77136dd8c7.js",
    "a8ff101f5ce3b1b48ab3.js",
    "ad785722db1783792c64.js",
    "b2cc4e1ee4c2836b836a.js",
    "b4c360ce821613a63e1b.js",
    "b746d4cc2dc0ab00733e.js",
    "bbd4cd22d833e0692cd9.js",
    "c0b4c1673ad9346c55ed.js",
    "c30da9b7027f2249d20c.js",
    "c86dc8b58cc67c4e20b4.js",
    "cff5cc432f0e55792e33.js",
    "d1dfbbf09158a9998b4f.js",
    "d644d3c1963281a6d652.js",
    "d96dfe1dd1799e1795e9.js",
    "da81bc70878f076cecde.js",
    "e0c75d23f0c37cda204a.js",
    "eb287ecebbcf1da088da.js",
    "eb30904e1fee603d2350.js",
    "f21aaad7776207136774.js",
    "f2f5e390dc17bf77c921.js",
    "f344b8f59173747c334b.js",
    "f4d3e419cab28b72017d.js",
    "fa29f9967d3fec15c8f5.js",
    "fb1f8025b0d5a05e0ad6.js",
    "fe8eb36dc9075a263c6b.js"
  ],
  "modules": {
    "11728309": [
      40
    ],
    "28821598": [
      38
    ],
    "34841288": [
      55
    ],
    "37124858": [
      40
    ],
    "40608692": [
      40
    ],
    "44369996": [
      59
    ],
    "46985617": [
      55
    ],
    "47088643": [
      49,
      77,
      72,
      76,
      70,
      78,
      74,
      75,
      71,
      73
    ],
    "47111762": [
      40
    ],
    "48350268": [
      40
    ],
    "57521574": [
      65
    ],
    "70521141": [
      34
    ],
    "70858294": [
      32
    ],
    "74135972": [
      40
    ],
    "75725096": [
      22
    ],
    "82532084": [
      22
    ],
    "89432000": [
      59
    ],
    "89952310": [
      34
    ],
    "91772144": [
      59
    ],
    "251c1f1f": [
      59
    ],
    "3e52c843": [
      40
    ],
    "02737301": [
      59
    ],
    "608c6e00": [
      59
    ],
    "1e30d9ec": [
      59
    ],
    "3a979740": [
      59
    ],
    "203e843b": [
      59
    ],
    "4c87c500": [
      59
    ],
    "092b35ca": [
      59
    ],
    "609c3ffd": [
      59
    ],
    "4b0f627f": [
      40
    ],
    "cbb1a456": [
      40
    ],
    "6a92ff4a": [
      59
    ],
    "2fc64065": [
      59
    ],
    "da5ee3cc": [
      59
    ],
    "3488f72b": [
      59
    ],
    "266cabfe": [
      59
    ],
    "2c13272d": [
      40
    ],
    "2f32c4b4": [
      59
    ],
    "0e71f8ba": [
      59
    ],
    "742e48e8": [
      59
    ],
    "d43bcb20": [
      59
    ],
    "d9423426": [
      59
    ],
    "4666d1a5": [
      59
    ],
    "9722f9f2": [
      59
    ],
    "c317d054": [
      59
    ],
    "3e9df6c5": [
      59
    ],
    "8a3be106": [
      59
    ],
    "6d964119": [
      59
    ],
    "021fce3c": [
      59
    ],
    "3eec9af8": [
      59
    ],
    "3fbefe4c": [
      59
    ],
    "247257bd": [
      59
    ],
    "222cc903": [
      59
    ],
    "8e130838": [
      59
    ],
    "5cffbc2f": [
      59
    ],
    "4540f6cc": [
      59
    ],
    "61ab900e": [
      59
    ],
    "41e1cdd6": [
      59
    ],
    "683a8a80": [
      40
    ],
    "3f0c1693": [
      59
    ],
    "459d249e": [
      59
    ],
    "5050e056": [
      59
    ],
    "44820e2b": [
      59
    ],
    "c5c93bcc": [
      59
    ],
    "5020f015": [
      59
    ],
    "0ac81912": [
      59
    ],
    "baeb5ed0": [
      59
    ],
    "563cb0ac": [
      49,
      77,
      72,
      76,
      70,
      78,
      74,
      75,
      71,
      73
    ],
    "d7d75714": [
      49,
      77,
      72,
      76,
      70,
      78,
      74,
      75,
      71,
      73
    ],
    "0b3cfb1e": [
      40
    ],
    "a494f0ea": [
      40
    ],
    "505bb544": [
      40
    ],
    "573fd38c": [
      59
    ],
    "104f016a": [
      59
    ],
    "3636377b": [
      59
    ],
    "7340a268": [
      59
    ],
    "6ee3794b": [
      59
    ],
    "0c6059b0": [
      59
    ],
    "96feb6d2": [
      59
    ],
    "da5327d0": [
      59
    ],
    "ae673c2c": [
      59
    ],
    "977bde34": [
      59
    ],
    "104a75b4": [
      59
    ],
    "0b414b4e": [
      59
    ],
    "6a8fa260": [
      59
    ],
    "a06ca0ec": [
      59
    ],
    "916719b4": [
      59
    ],
    "90ff041a": [
      59
    ],
    "2e1b4cf6": [
      59
    ],
    "0684c2a4": [
      40
    ],
    "4e4962f6": [
      40
    ],
    "775bca4b": [
      59
    ],
    "101b7d60": [
      49,
      77,
      72,
      76,
      70,
      78,
      74,
      75,
      71,
      73
    ],
    "4c013c35": [
      59
    ],
    "11a0f3b1": [
      59
    ],
    "c2717b1a": [
      40
    ],
    "1be96e16": [
      59
    ],
    "105818d6": [
      59
    ],
    "af7b1db6": [
      59
    ],
    "51f53a31": [
      59
    ],
    "11c5a049": [
      59
    ],
    "fe5bbaa0": [
      59
    ],
    "ed8afb22": [
      59
    ],
    "6f05b898": [
      59
    ],
    "1172b107": [
      59
    ],
    "36487a50": [
      59
    ],
    "b2b39238": [
      59
    ],
    "c7a6f6b4": [
      59
    ],
    "0bb2e22c": [
      59
    ],
    "1c034eb9": [
      59
    ],
    "5efaeb9c": [
      59
    ],
    "a5eb8caa": [
      59
    ],
    "981c7192": [
      59
    ],
    "015902ca": [
      59
    ],
    "dacb1290": [
      59
    ],
    "ca6a7df6": [
      59
    ],
    "57cb03e4": [
      59
    ],
    "2db0c0f4": [
      59
    ],
    "7d5b1a2b": [
      59
    ],
    "5c0e84d9": [
      40
    ],
    "73d73bb3": [
      40
    ],
    "750bdb3b": [
      40
    ],
    "8906d540": [
      40
    ],
    "f0c7ec38": [
      40
    ],
    "0e25cead": [
      40
    ],
    "46de54eb": [
      40
    ],
    "fc59b018": [
      40
    ],
    "3a7f9014": [
      59
    ],
    "30e52986": [
      59
    ],
    "2e7d0a61": [
      59
    ],
    "65a7c710": [
      59
    ],
    "0f9087a2": [
      59
    ],
    "572a8596": [
      59
    ],
    "ee61cc2e": [
      40
    ],
    "6b9f211a": [
      40
    ],
    "e842117c": [
      40
    ],
    "14336ffd": [
      40
    ],
    "6ab5e4e8": [
      40
    ],
    "4f737b0f": [
      40
    ],
    "12ae8975": [
      59
    ],
    "309a5e3c": [
      59
    ],
    "9c007872": [
      59
    ],
    "1f2e0ab1": [
      59
    ],
    "2ccaae9a": [
      59
    ],
    "e8f739b2": [
      49,
      77,
      72,
      76,
      70,
      78,
      74,
      75,
      71,
      73
    ],
    "0da630e4": [
      59
    ],
    "6dbf7014": [
      59
    ],
    "eb57599e": [
      59
    ],
    "6385ff52": [
      59
    ],
    "d42b5b6c": [
      59
    ],
    "cc0abd82": [
      59
    ],
    "10af55f7": [
      59
    ],
    "46dcda3e": [
      59
    ],
    "3c3788ca": [
      59
    ],
    "d2e84f04": [
      59
    ],
    "22ee8022": [
      59
    ],
    "003c3bd9": [
      59
    ],
    "76c8f7ac": [
      59
    ],
    "06945934": [
      59
    ],
    "281ce3ac": [
      59
    ],
    "a38180e0": [
      59
    ],
    "196802c6": [
      59
    ],
    "c0ff2612": [
      59
    ],
    "5430ef7e": [
      59
    ],
    "63de770c": [
      59
    ],
    "7780162d": [
      59
    ],
    "666a2c87": [
      59
    ],
    "3015d283": [
      59
    ],
    "4a53ad56": [
      49,
      77,
      72,
      76,
      70,
      78,
      74,
      75,
      71,
      73
    ],
    "0229f7c3": [
      49,
      77,
      72,
      76,
      70,
      78,
      74,
      75,
      71,
      73
    ],
    "0bb1f875": [
      59
    ],
    "2bf92ffc": [
      59
    ],
    "0d05e248": [
      59
    ],
    "1c6dc3fc": [
      59
    ],
    "7b584a98": [
      59
    ],
    "398db637": [
      59
    ],
    "5edc8245": [
      59
    ],
    "7744bea2": [
      59
    ],
    "dfb2aa36": [
      59
    ],
    "03730764": [
      59
    ],
    "420022c4": [
      49,
      77,
      72,
      76,
      70,
      78,
      74,
      75,
      71,
      73
    ],
    "094c7742": [
      49,
      77,
      72,
      76,
      70,
      78,
      74,
      75,
      71,
      73
    ],
    "e086a32c": [
      49,
      77,
      72,
      76,
      70,
      78,
      74,
      75,
      71,
      73
    ],
    "060fd02a": [
      49,
      77,
      72,
      76,
      70,
      78,
      74,
      75,
      71,
      73
    ],
    "65473d62": [
      40
    ],
    "4e23cf78": [
      40
    ],
    "fca28eba": [
      40
    ],
    "5666f05c": [
      49,
      77,
      72,
      76,
      70,
      78,
      74,
      75,
      71,
      73
    ],
    "38c662bb": [
      49,
      77,
      72,
      76,
      70,
      78,
      74,
      75,
      71,
      73
    ],
    "eabf2cda": [
      40
    ],
    "1c136260": [
      49,
      77,
      72,
      76,
      70,
      78,
      74,
      75,
      71,
      73
    ],
    "1eb73ff6": [
      49,
      77,
      72,
      76,
      70,
      78,
      74,
      75,
      71,
      73
    ],
    "53924c66": [
      49,
      77,
      72,
      76,
      70,
      78,
      74,
      75,
      71,
      73
    ],
    "4f190eaa": [
      49,
      77,
      72,
      76,
      70,
      78,
      74,
      75,
      71,
      73
    ],
    "41677b1e": [
      49,
      77,
      72,
      76,
      70,
      78,
      74,
      75,
      71,
      73
    ],
    "f374e76e": [
      49,
      77,
      72,
      76,
      70,
      78,
      74,
      75,
      71,
      73
    ],
    "255d1509": [
      49,
      77,
      72,
      76,
      70,
      78,
      74,
      75,
      71,
      73
    ],
    "1002aa1e": [
      49,
      77,
      72,
      76,
      70,
      78,
      74,
      75,
      71,
      73
    ],
    "639cfd3e": [
      49,
      77,
      72,
      76,
      70,
      78,
      74,
      75,
      71,
      73
    ],
    "13db5bcf": [
      49,
      77,
      72,
      76,
      70,
      78,
      74,
      75,
      71,
      73
    ],
    "8edf99a8": [
      49,
      77,
      72,
      76,
      70,
      78,
      74,
      75,
      71,
      73
    ],
    "dd378de8": [
      59
    ],
    "a638e0fe": [
      59
    ],
    "37d7562e": [
      59
    ],
    "043eb0ea": [
      59
    ],
    "002958f3": [
      49,
      77,
      72,
      76,
      70,
      78,
      74,
      75,
      71,
      73
    ],
    "4e6c3590": [
      49,
      77,
      72,
      76,
      70,
      78,
      74,
      75,
      71,
      73
    ],
    "75dd0917": [
      40
    ],
    "0dec4ea3": [
      40
    ],
    "f99f68e4": [
      40
    ],
    "308135c4": [
      49,
      77,
      72,
      76,
      70,
      78,
      74,
      75,
      71,
      73
    ],
    "56f97723": [
      49,
      77,
      72,
      76,
      70,
      78,
      74,
      75,
      71,
      73
    ],
    "2603a8d4": [
      49,
      77,
      72,
      76,
      70,
      78,
      74,
      75,
      71,
      73
    ],
    "215ac50c": [
      40
    ],
    "0e6d7858": [
      40
    ],
    "ddb1fbda": [
      40
    ],
    "55f7ff3b": [
      40
    ],
    "b9861edc": [
      40
    ],
    "98221b9c": [
      40
    ],
    "00d0628e": [
      40
    ],
    "cf4e2e86": [
      40
    ],
    "3dedae56": [
      40
    ],
    "395f918b": [
      40
    ],
    "0c8fcf9e": [
      40
    ],
    "3eb183a7": [
      40
    ],
    "10e5fbcd": [
      40
    ],
    "872f6c82": [
      40
    ],
    "39f2f2eb": [
      40
    ],
    "28d855eb": [
      40
    ],
    "3ba0913d": [
      40
    ],
    "612da156": [
      40
    ],
    "f216f216": [
      40
    ],
    "598c1149": [
      40
    ],
    "7625a13a": [
      40
    ],
    "1465219a": [
      40
    ],
    "a3be7ece": [
      40
    ],
    "4da8ee57": [
      40
    ],
    "9ddd4c12": [
      40
    ],
    "22c75fc8": [
      40
    ],
    "fe541770": [
      40
    ],
    "3638df06": [
      40
    ],
    "68877aa6": [
      40
    ],
    "3c8d1360": [
      40
    ],
    "0c1080cd": [
      40
    ],
    "6d85440c": [
      40
    ],
    "704aa10c": [
      40
    ],
    "4e2b78ae": [
      40
    ],
    "2226e6c5": [
      40
    ],
    "c97b19ba": [
      40
    ],
    "55e98fca": [
      40
    ],
    "5f100d0f": [
      40
    ],
    "d4007862": [
      40
    ],
    "0b5a0d94": [
      40
    ],
    "549b573a": [
      40
    ],
    "2ddcc427": [
      40
    ],
    "ec430cde": [
      40
    ],
    "2e475326": [
      40
    ],
    "7ffd0f28": [
      40
    ],
    "192f91bf": [
      40
    ],
    "1ae5d3f2": [
      40
    ],
    "4e4e80f8": [
      40
    ],
    "03f658b6": [
      40
    ],
    "74a70ff8": [
      40
    ],
    "486bd5ad": [
      40
    ],
    "1cac089d": [
      40
    ],
    "8fa7fdd6": [
      40
    ],
    "768781ec": [
      40
    ],
    "c38adb8a": [
      40
    ],
    "7b3fc470": [
      40
    ],
    "910a1d8a": [
      40
    ],
    "4d8200f0": [
      40
    ],
    "4710130e": [
      40
    ],
    "2def9724": [
      40
    ],
    "e03060ca": [
      59
    ],
    "c6f48a70": [
      59
    ],
    "0274a4b7": [
      59
    ],
    "3ba03f56": [
      59
    ],
    "4c2ce694": [
      59
    ],
    "7e093827": [
      59
    ],
    "6788cf92": [
      59
    ],
    "fcc8d9c0": [
      59
    ],
    "5414428a": [
      59
    ],
    "14db7da2": [
      59
    ],
    "29ad77a8": [
      59
    ],
    "644353f9": [
      59
    ],
    "12d99710": [
      59
    ],
    "9d76b452": [
      59
    ],
    "6edb3a6d": [
      59
    ],
    "102b5178": [
      59
    ],
    "0923fab3": [
      59
    ],
    "ccb440c6": [
      49,
      77,
      72,
      76,
      70,
      78,
      74,
      75,
      71,
      73
    ],
    "5e2ac602": [
      22
    ],
    "579404a6": [
      38
    ],
    "0a8305b5": [
      22
    ],
    "0a887a29": [
      22
    ],
    "840b27bc": [
      22
    ],
    "834898e8": [
      22
    ],
    "832a986a": [
      22
    ],
    "83243b38": [
      22
    ],
    "827b212c": [
      22
    ],
    "0a8c1d21": [
      22
    ],
    "0a90a8d7": [
      22
    ],
    "0a919195": [
      22
    ],
    "0a944bcf": [
      22
    ],
    "0a94c02e": [
      22
    ],
    "0a95348d": [
      22
    ],
    "0a9691aa": [
      22
    ],
    "0a970609": [
      22
    ],
    "0a9ceedc": [
      22
    ],
    "0aa51d8a": [
      22
    ],
    "0aa67aa7": [
      22
    ],
    "0aa7d7c4": [
      22
    ],
    "0aab065d": [
      22
    ],
    "0aacd7d9": [
      22
    ],
    "45bfefb5": [
      22
    ],
    "45d6aa43": [
      22
    ],
    "0ab49228": [
      22
    ],
    "0abe1df3": [
      22
    ],
    "ee4117c8": [
      22
    ],
    "ec8cb388": [
      22
    ],
    "ec66845c": [
      22
    ],
    "ebf4df96": [
      22
    ],
    "ebb9c758": [
      22
    ],
    "ebb36a26": [
      22
    ],
    "eb19c4b8": [
      22
    ],
    "0abf7b10": [
      22
    ],
    "0ac14c8c": [
      22
    ],
    "db3f4a6c": [
      22
    ],
    "d95c8852": [
      22
    ],
    "0ac1c0eb": [
      22
    ],
    "0ac2354a": [
      22
    ],
    "0ac7355f": [
      22
    ],
    "0acad857": [
      22
    ],
    "0acd9291": [
      22
    ],
    "0aceefae": [
      22
    ],
    "756bf364": [
      22
    ],
    "0ad21e47": [
      22
    ],
    "0ad54ce0": [
      22
    ],
    "0ad6a9fd": [
      22
    ],
    "0ada4cf5": [
      22
    ],
    "67b8693a": [
      22
    ],
    "0ade644c": [
      22
    ],
    "0ae535dd": [
      22
    ],
    "0ae70759": [
      22
    ],
    "0aeb1eb0": [
      22
    ],
    "0aec7bcd": [
      22
    ],
    "073e15ac": [
      22
    ],
    "0af2d8ff": [
      22
    ],
    "0af9aa90": [
      22
    ],
    "0afa1eef": [
      22
    ],
    "66ba036d": [
      22
    ],
    "0aff9363": [
      22
    ],
    "0b091f2e": [
      22
    ],
    "0b0daae4": [
      22
    ],
    "0b12369a": [
      22
    ],
    "0b131f58": [
      22
    ],
    "0b1393b7": [
      22
    ],
    "0b140816": [
      22
    ],
    "0b16c250": [
      22
    ],
    "0b1893cc": [
      22
    ],
    "0b1c36c4": [
      22
    ],
    "0b221f97": [
      22
    ],
    "0b246572": [
      22
    ],
    "0b254e30": [
      22
    ],
    "0b2bab62": [
      22
    ],
    "0b2d7cde": [
      22
    ],
    "0b2e659c": [
      22
    ],
    "0b2ed9fb": [
      22
    ],
    "0b2fc2b9": [
      22
    ],
    "0b319435": [
      22
    ],
    "0b320894": [
      22
    ],
    "5c25bdfe": [
      22
    ],
    "0b327cf3": [
      22
    ],
    "0b34c2ce": [
      22
    ],
    "0b3865c6": [
      22
    ],
    "0b39c2e3": [
      22
    ],
    "0b3cf17c": [
      22
    ],
    "7242d5bc": [
      22
    ],
    "0b3dda3a": [
      22
    ],
    "51231ef3": [
      22
    ],
    "0b59207e": [
      22
    ],
    "0b5cc376": [
      22
    ],
    "3dd8b1bb": [
      22
    ],
    "0b76ac9d": [
      22
    ],
    "0b7966d7": [
      22
    ],
    "0b7fc409": [
      22
    ],
    "0b803868": [
      22
    ],
    "0b8209e4": [
      22
    ],
    "0b82f2a2": [
      22
    ],
    "0b836701": [
      22
    ],
    "0b85acdc": [
      22
    ],
    "0b86213b": [
      22
    ],
    "235cfd36": [
      22
    ],
    "0b86959a": [
      22
    ],
    "0b87f2b7": [
      22
    ],
    "0b886716": [
      22
    ],
    "0b8c7e6d": [
      22
    ],
    "0b8e4fe9": [
      22
    ],
    "665a9d51": [
      22
    ],
    "0b8f38a7": [
      22
    ],
    "0b8fad06": [
      22
    ],
    "36ec4887": [
      22
    ],
    "66b7cd64": [
      22
    ],
    "0b9438bc": [
      22
    ],
    "677ee7ee": [
      22
    ],
    "677f5c4d": [
      22
    ],
    "4a2e88f6": [
      22
    ],
    "d4cc5464": [
      22
    ],
    "0b9f21a4": [
      22
    ],
    "0ba2503d": [
      22
    ],
    "0ba5f335": [
      22
    ],
    "6154359d": [
      22
    ],
    "0bac5067": [
      22
    ],
    "f08f47b2": [
      22
    ],
    "0bd95124": [
      22
    ],
    "5c341d2c": [
      22
    ],
    "5ba9ec5c": [
      22
    ],
    "5a4ccf5c": [
      22
    ],
    "77a8f7ac": [
      34
    ],
    "6256c644": [
      34
    ],
    "bfac3e80": [
      34
    ],
    "4247d911": [
      34
    ],
    "5d835b51": [
      34
    ],
    "5fd391c1": [
      34
    ],
    "73e882c7": [
      34
    ],
    "2cb3cdf6": [
      34
    ],
    "a9708426": [
      34
    ],
    "5fc955bf": [
      47
    ],
    "bb90e9e2": [
      34
    ],
    "4d192fec": [
      34
    ],
    "731dd8a9": [
      34
    ],
    "bc8379fc": [
      34
    ],
    "33602d29": [
      34
    ],
    "203dc574": [
      34
    ],
    "6b4abe47": [
      38
    ],
    "6b5032bb": [
      38
    ],
    "27ba1250": [
      38
    ],
    "281b59ba": [
      38
    ],
    "282a59f9": [
      38
    ],
    "282d8892": [
      38
    ],
    "289615ec": [
      38
    ],
    "6b53d5b3": [
      38
    ],
    "6b586169": [
      38
    ],
    "6b594a27": [
      38
    ],
    "6b5c0461": [
      38
    ],
    "6b5c78c0": [
      38
    ],
    "6b5ced1f": [
      38
    ],
    "6b5e4a3c": [
      38
    ],
    "6b5ebe9b": [
      38
    ],
    "6b64a76e": [
      38
    ],
    "6b6cd61c": [
      38
    ],
    "6b6e3339": [
      38
    ],
    "6b6f9056": [
      38
    ],
    "6b72beef": [
      38
    ],
    "6b74906b": [
      38
    ],
    "a100d43a": [
      38
    ],
    "a0d35f1e": [
      38
    ],
    "6b7c4aba": [
      38
    ],
    "6b85d685": [
      38
    ],
    "1ac1cb6c": [
      38
    ],
    "190d672c": [
      38
    ],
    "18e73800": [
      38
    ],
    "1875933a": [
      38
    ],
    "183a7afc": [
      38
    ],
    "18341dca": [
      38
    ],
    "179a785c": [
      38
    ],
    "6b8733a2": [
      38
    ],
    "6b89051e": [
      38
    ],
    "07bffe10": [
      38
    ],
    "05dd3bf6": [
      38
    ],
    "6b89797d": [
      38
    ],
    "6b89eddc": [
      38
    ],
    "6b8eedf1": [
      38
    ],
    "6b9290e9": [
      38
    ],
    "6b954b23": [
      38
    ],
    "6b96a840": [
      38
    ],
    "2f067de3": [
      38
    ],
    "2f09ac7c": [
      38
    ],
    "6b99d6d9": [
      38
    ],
    "6b9d0572": [
      38
    ],
    "6b9e628f": [
      38
    ],
    "6ba20587": [
      38
    ],
    "3ce16316": [
      38
    ],
    "6ba61cde": [
      38
    ],
    "6bacee6f": [
      38
    ],
    "6baebfeb": [
      38
    ],
    "6bb2d742": [
      38
    ],
    "6bb4345f": [
      38
    ],
    "70fdbbda": [
      38
    ],
    "6bba9191": [
      38
    ],
    "6bc16322": [
      38
    ],
    "6bc1d781": [
      38
    ],
    "5f0cacca": [
      38
    ],
    "6bc74bf5": [
      38
    ],
    "6bd0d7c0": [
      38
    ],
    "6bd56376": [
      38
    ],
    "6bd9ef2c": [
      38
    ],
    "6bdad7ea": [
      38
    ],
    "6bdb4c49": [
      38
    ],
    "6bdbc0a8": [
      38
    ],
    "6bde7ae2": [
      38
    ],
    "6be04c5e": [
      38
    ],
    "6be3ef56": [
      38
    ],
    "6be9d829": [
      38
    ],
    "6bec1e04": [
      38
    ],
    "6bed06c2": [
      38
    ],
    "6bf363f4": [
      38
    ],
    "6bf53570": [
      38
    ],
    "6bf61e2e": [
      38
    ],
    "6bf6928d": [
      38
    ],
    "6bf77b4b": [
      38
    ],
    "6bf94cc7": [
      38
    ],
    "6bf9c126": [
      38
    ],
    "3bacc72f": [
      38
    ],
    "6bfa3585": [
      38
    ],
    "6bfc7b60": [
      38
    ],
    "6c001e58": [
      38
    ],
    "6c017b75": [
      38
    ],
    "6c04aa0e": [
      38
    ],
    "309e3b50": [
      38
    ],
    "6c0592cc": [
      38
    ],
    "8a3a75be": [
      38
    ],
    "6c20d910": [
      38
    ],
    "6c247c08": [
      38
    ],
    "b0cf502e": [
      38
    ],
    "6c3e652f": [
      38
    ],
    "6c411f69": [
      38
    ],
    "6c477c9b": [
      38
    ],
    "6c47f0fa": [
      38
    ],
    "6c49c276": [
      38
    ],
    "6c4aab34": [
      38
    ],
    "6c4b1f93": [
      38
    ],
    "6c4d656e": [
      38
    ],
    "6c4dd9cd": [
      38
    ],
    "1bcbcfe4": [
      38
    ],
    "6c4e4e2c": [
      38
    ],
    "6c4fab49": [
      38
    ],
    "6c501fa8": [
      38
    ],
    "6c5436ff": [
      38
    ],
    "6c56087b": [
      38
    ],
    "1e89f6ff": [
      38
    ],
    "6c56f139": [
      38
    ],
    "6c576598": [
      38
    ],
    "bea82296": [
      38
    ],
    "1ee72712": [
      38
    ],
    "6c5bf14e": [
      38
    ],
    "1fae419c": [
      38
    ],
    "1faeb5fb": [
      38
    ],
    "1f5782d2": [
      38
    ],
    "014d0808": [
      38
    ],
    "6c66da36": [
      38
    ],
    "6c6a08cf": [
      38
    ],
    "6c6dabc7": [
      38
    ],
    "59c3084b": [
      38
    ],
    "6c7408f9": [
      38
    ],
    "c5b8418e": [
      38
    ],
    "6ca109b6": [
      38
    ],
    "3ba59798": [
      38
    ],
    "3beab000": [
      38
    ],
    "3c993e80": [
      38
    ],
    "761e4f90": [
      34
    ],
    "741c45db": [
      34
    ],
    "1ae2ea85": [
      34
    ],
    "742d28ba": [
      34
    ],
    "2f50db4e": [
      64
    ],
    "dfc9bdb2": [
      50
    ],
    "719b1e1c": [
      19
    ],
    "2cf6999f": [
      67
    ],
    "006b6a4b": [
      24
    ],
    "1d4bc8f2": [
      25
    ],
    "0c6fde5d": [
      61
    ],
    "7eab927b": [
      10
    ],
    "3648b903": [
      33
    ],
    "b3278676": [
      29
    ],
    "e460d182": [
      30
    ],
    "bcc838a6": [
      56
    ],
    "2bcd95b2": [
      43
    ],
    "7ada44a9": [
      48
    ],
    "03ed8449": [
      18
    ],
    "86b9103c": [
      51
    ],
    "747ae585": [
      51
    ],
    "249b6d80": [
      65
    ],
    "6d1fc508": [
      45
    ],
    "14e42f8e": [
      55
    ],
    "6ba5ae0e": [
      34
    ],
    "55ba8071": [
      34
    ],
    "5b9beb82": [
      34
    ],
    "5fde45d7": [
      34
    ],
    "5ef02e28": [
      34
    ],
    "2ac568be": [
      34
    ],
    "05af7392": [
      34
    ],
    "7058e2d2": [
      34
    ],
    "508db1f5": [
      55
    ],
    "4300e274": [
      34
    ],
    "6e4a9450": [
      34
    ],
    "4c43fd0c": [
      34
    ],
    "6a31ddbc": [
      53
    ],
    "0c213a01": [
      23
    ],
    "a73d875c": [
      8
    ],
    "45403bf4": [
      35
    ],
    "477d6eae": [
      36
    ],
    "12aba117": [
      36
    ],
    "65f3e3ea": [
      15
    ],
    "01246853": [
      13
    ],
    "8365e6a2": [
      52
    ],
    "59e97d84": [
      46
    ],
    "9b31f150": [
      58
    ],
    "58597efa": [
      44
    ],
    "7cb6ddb6": [
      3
    ],
    "62348c71": [
      4
    ],
    "212b9725": [
      12
    ],
    "5d4bfb73": [
      20
    ],
    "72e05163": [
      54
    ],
    "7eae0c2f": [
      11
    ],
    "e5b619f6": [
      68
    ],
    "dffcd464": [
      42
    ],
    "77c524c0": [
      32
    ],
    "4c365771": [
      62
    ],
    "b0f178c2": [
      26
    ],
    "2cbf6205": [
      38
    ],
    "17a02f34": [
      34
    ],
    "55e9d981": [
      55
    ],
    "560924a4": [
      34
    ],
    "4b44ab6c": [
      34
    ],
    "37814ffc": [
      34
    ],
    "8c45964a": [
      34
    ],
    "71a87843": [
      34
    ],
    "721fc89a": [
      34
    ],
    "0631edc6": [
      34
    ],
    "01b8a01b": [
      34
    ],
    "56c76856": [
      34
    ],
    "4378aba1": [
      34
    ],
    "70569cf7": [
      34
    ],
    "6ca9e436": [
      64
    ],
    "3f841bc2": [
      64
    ],
    "4e0b445a": [
      50
    ],
    "f43acbca": [
      50
    ],
    "8c265348": [
      50
    ],
    "3f22fa10": [
      19
    ],
    "31090e53": [
      19
    ],
    "0b0314da": [
      67
    ],
    "2736ec54": [
      67
    ],
    "18344d3f": [
      24
    ],
    "24438fc2": [
      24
    ],
    "02c17704": [
      25
    ],
    "7478525b": [
      25
    ],
    "24794c2e": [
      61
    ],
    "639c67c6": [
      61
    ],
    "590e5b07": [
      10
    ],
    "864934b8": [
      10
    ],
    "7d6d3012": [
      33
    ],
    "5c09110c": [
      33
    ],
    "f0808f5e": [
      29
    ],
    "04ce73a4": [
      29
    ],
    "68325fcb": [
      30
    ],
    "68012b30": [
      30
    ],
    "2c9c92a1": [
      56
    ],
    "3d4ea224": [
      56
    ],
    "00e2c53e": [
      43
    ],
    "0672a61b": [
      43
    ],
    "85aded9e": [
      38
    ],
    "6fa2083d": [
      38
    ],
    "c20ec996": [
      48
    ],
    "1be1a252": [
      48
    ],
    "36a42c3d": [
      18
    ],
    "091f4d80": [
      18
    ],
    "bdaa1724": [
      51
    ],
    "fb73dbea": [
      51
    ],
    "1038d779": [
      51
    ],
    "0dc9c20c": [
      51
    ],
    "29cd36b7": [
      65
    ],
    "d1fe4120": [
      45
    ],
    "436d1a33": [
      45
    ],
    "f75f7a3c": [
      53
    ],
    "3a2191ec": [
      53
    ],
    "015216f4": [
      34
    ],
    "8167b3dc": [
      55
    ],
    "2594862a": [
      55
    ],
    "066d93a1": [
      55
    ],
    "07fbd35c": [
      34
    ],
    "0a2f5baa": [
      34
    ],
    "fb98ea02": [
      34
    ],
    "745be2ce": [
      34
    ],
    "12876d24": [
      34
    ],
    "688f0046": [
      34
    ],
    "b1f605a4": [
      55
    ],
    "0e2e4f53": [
      34
    ],
    "d9588948": [
      34
    ],
    "71ab053a": [
      34
    ],
    "06d1c4ca": [
      34
    ],
    "731ae2b8": [
      34
    ],
    "0bee7d2b": [
      34
    ],
    "1b812fb2": [
      34
    ],
    "3a9e7c58": [
      34
    ],
    "00a6bb88": [
      34
    ],
    "78d32636": [
      34
    ],
    "46aa031c": [
      34
    ],
    "f03ffb08": [
      34
    ],
    "422f6b9a": [
      34
    ],
    "63bee937": [
      34
    ],
    "2e342d05": [
      34
    ],
    "1f95b86f": [
      34
    ],
    "20a73dda": [
      55
    ],
    "3323d5ce": [
      55
    ],
    "5893c165": [
      55
    ],
    "1ae5a8aa": [
      55
    ],
    "2da8662a": [
      55
    ],
    "235c225b": [
      55
    ],
    "0b4d4154": [
      34
    ],
    "1fcdb094": [
      34
    ],
    "1554183a": [
      34
    ],
    "bb24480c": [
      34
    ],
    "ade51dac": [
      34
    ],
    "2c3f2494": [
      55
    ],
    "1171b18e": [
      34
    ],
    "625efe1e": [
      34
    ],
    "a7078c2a": [
      34
    ],
    "03d5f08d": [
      34
    ],
    "876284ba": [
      34
    ],
    "0d8c999c": [
      34
    ],
    "5c60e932": [
      34
    ],
    "12ab79e4": [
      34
    ],
    "41299ae8": [
      55
    ],
    "a34a98a4": [
      53
    ],
    "0d91b06a": [
      53
    ],
    "7e1782f5": [
      23
    ],
    "d8286810": [
      23
    ],
    "fd132844": [
      8
    ],
    "f1f3668a": [
      8
    ],
    "829944dc": [
      35
    ],
    "348c6b6f": [
      35
    ],
    "5806bcff": [
      15
    ],
    "68b8cc82": [
      15
    ],
    "6295ab72": [
      13
    ],
    "7b21650a": [
      13
    ],
    "6ab521a3": [
      52
    ],
    "a60490b4": [
      52
    ],
    "7f735632": [
      46
    ],
    "7c882796": [
      46
    ],
    "f1079238": [
      58
    ],
    "e5e7d07e": [
      58
    ],
    "0111af86": [
      44
    ],
    "45b7e023": [
      44
    ],
    "5758909e": [
      3
    ],
    "2ce6f8d0": [
      3
    ],
    "baf0d224": [
      16
    ],
    "2fbc6865": [
      4
    ],
    "21a27ca8": [
      4
    ],
    "2403269e": [
      12
    ],
    "da9977e4": [
      12
    ],
    "3de684ff": [
      20
    ],
    "44b0af5c": [
      20
    ],
    "5767cdef": [
      54
    ],
    "3882eb8c": [
      54
    ],
    "2b162123": [
      11
    ],
    "6d5eb726": [
      11
    ],
    "8048ca0e": [
      68
    ],
    "db528788": [
      68
    ],
    "7489125a": [
      42
    ],
    "55a42ff7": [
      42
    ],
    "9a63ced2": [
      32
    ],
    "2cd0e0fd": [
      62
    ],
    "339b0b5a": [
      62
    ],
    "0733be93": [
      26
    ],
    "276b9b16": [
      26
    ],
    "111c2e16": [
      16
    ],
    "7ea2f9d9": [
      36
    ],
    "d444649e": [
      36
    ],
    "fa5c0642": [
      64
    ],
    "f575fb34": [
      50
    ],
    "bb8abcea": [
      19
    ],
    "5769b1f2": [
      67
    ],
    "351954bc": [
      24
    ],
    "6c317abb": [
      25
    ],
    "097cc534": [
      14
    ],
    "c71d9ad6": [
      61
    ],
    "6fef20da": [
      10
    ],
    "7d17afb9": [
      33
    ],
    "4c8795d9": [
      29
    ],
    "161a1bb4": [
      30
    ],
    "c97f2bba": [
      56
    ],
    "750d8839": [
      43
    ],
    "45602a1a": [
      48
    ],
    "b0855d96": [
      63
    ],
    "08647634": [
      18
    ],
    "8b787c6e": [
      51
    ],
    "c48fc576": [
      17
    ],
    "d75fae9c": [
      65
    ],
    "7a53ec5c": [
      45
    ],
    "7da6f0bc": [
      53
    ],
    "08d9152e": [
      23
    ],
    "1acbcfe2": [
      8
    ],
    "01475fac": [
      27
    ],
    "40b1f504": [
      5
    ],
    "baec50b8": [
      35
    ],
    "536248f6": [
      15
    ],
    "5f4aa5aa": [
      13
    ],
    "3e7db530": [
      52
    ],
    "33ff1994": [
      46
    ],
    "dd634148": [
      58
    ],
    "acb5ee5a": [
      44
    ],
    "2ec3871f": [
      3
    ],
    "e0d74610": [
      4
    ],
    "47cf452a": [
      12
    ],
    "2438ef5a": [
      2
    ],
    "214af1c0": [
      20
    ],
    "419a2817": [
      39
    ],
    "1d9aca18": [
      54
    ],
    "d8b96690": [
      11
    ],
    "1952f6ff": [
      68
    ],
    "367eca4d": [
      7
    ],
    "785467d8": [
      42
    ],
    "5b3ec4f4": [
      32
    ],
    "75b1ef64": [
      62
    ],
    "4f30e3f6": [
      60
    ],
    "c5530a26": [
      26
    ],
    "69049bde": [
      37
    ],
    "6a9264da": [
      31
    ],
    "7910d553": [
      6
    ],
    "28e05004": [
      28
    ]
  },
  "assetsMapping": {
    "01d7f9d27eba7963df98.js": "bba68bf6",
    "06808358708e16107f18.js": "bba68bf6",
    "06f03e3ab48b2fe3c4ae.js": "bba68bf6",
    "07d5f8d6bd27d8986f3b.js": "7d0cd5f2",
    "08f34f8696c8f9dbeadb.js": "8a645d80",
    "0a13e0e6604faff23163.js": "bba68bf6",
    "11d2e6b9ac34f8d62a81.js": "38db2962",
    "161aa66f3cc68b4e2e52.js": "bba68bf6",
    "1b3a8e6f556870fc5881.js": "fead3ff2",
    "1dac18841524e3958b39.js": "bba68bf6",
    "20112602d2f6691dd0d4.js": "bba68bf6",
    "26a830646733ead97e3d.js": "bba68bf6",
    "2c0f8532e87016ce41d2.js": "6e246492",
    "2f3c4df1ae08bc03e36a.js": "bba68bf6",
    "36ad12cd4d7174123316.js": "bba68bf6",
    "36f5c75301bd2564e5cf.js": "f46e961c",
    "512723d3b11b19cfa16e.js": "863da92e",
    "51417af977e5b8ef8dbc.js": "14bd6d8e",
    "53e70fcc006def71c01c.js": "bba68bf6",
    "54a7108a1652b686d5c2.js": "6fca0322",
    "5633b8480f31fbd5a51e.js": "bba68bf6",
    "5a2365d28863482a6c7b.js": "06ad6b2c",
    "5eaf4242196a7f2f03b6.js": "b70bdd02",
    "636be5046d8705b5a92d.js": "29bd80b0",
    "6a51f1bae46034d6c0bc.js": "bba68bf6",
    "6b4ee8adb9e01183dfcd.js": "7e0eb86d",
    "721f58e0b7e9d886ff3d.js": "37ceeafe",
    "72f205a2c97ec972885d.js": "28e4cc74",
    "75c18969087c74f071a5.js": "4630503e",
    "77a663722b3ce1f93f3b.js": "d1e1aa46",
    "7a1418d0beef6763fb18.js": "bba68bf6",
    "8282956f8842e47fec94.js": "0375e7fc",
    "830745f8a4b5dbbf4023.js": "bba68bf6",
    "842979e2fed04f812316.js": "2a130dde",
    "851e9a21e1d0294bcc09.js": "39196fc4",
    "867f245d4b107bb48f7f.js": "bba68bf6",
    "868bf46e1434b8beaba6.js": "7b844aaa",
    "954094794ad91a69e9c1.js": "bba68bf6",
    "955d21512d42eecf2099.js": "7ea1d828",
    "a240b5709022369269bf.js": "bba68bf6",
    "a2ee37bcfd77136dd8c7.js": "2533e726",
    "a8ff101f5ce3b1b48ab3.js": "bba68bf6",
    "ad785722db1783792c64.js": "5c34c35f",
    "b2cc4e1ee4c2836b836a.js": "bba68bf6",
    "b4c360ce821613a63e1b.js": "bba68bf6",
    "b746d4cc2dc0ab00733e.js": "6f411f20",
    "bb6cd6d6a15a1a806e1a.js": "1a3ae26b",
    "bbd4cd22d833e0692cd9.js": "9dee6b5a",
    "c0b4c1673ad9346c55ed.js": "70798914",
    "c30da9b7027f2249d20c.js": "bba68bf6",
    "c86dc8b58cc67c4e20b4.js": "6ddef32e",
    "cff5cc432f0e55792e33.js": "bba68bf6",
    "d1dfbbf09158a9998b4f.js": "bba68bf6",
    "d644d3c1963281a6d652.js": "03206766",
    "d96dfe1dd1799e1795e9.js": "bba68bf6",
    "da81bc70878f076cecde.js": "bba68bf6",
    "dec8311b2870f1340085.js": "0859c165",
    "e0c75d23f0c37cda204a.js": "bba68bf6",
    "eb287ecebbcf1da088da.js": "294a16fc",
    "eb30904e1fee603d2350.js": "bba68bf6",
    "f21aaad7776207136774.js": "732d9190",
    "f2f5e390dc17bf77c921.js": "2aff1868",
    "f344b8f59173747c334b.js": "6a655535",
    "f4d3e419cab28b72017d.js": "bba68bf6",
    "fa29f9967d3fec15c8f5.js": "5a04110a",
    "fb1f8025b0d5a05e0ad6.js": "bba68bf6",
    "fe8eb36dc9075a263c6b.js": "bba68bf6"
  }
}